qinteract/__init__.py
qinteract/process_interact.py
qinteract/socket_interact.py
qinteract-0.1.1.dist-info/METADATA
qinteract-0.1.1.dist-info/WHEEL
qinteract-0.1.1.dist-info/top_level.txt
qinteract-0.1.1.dist-info/RECORD
