Metadata-Version: 2.1
Name: qinteract
Version: 0.1.1
Summary: Process/Socket interactive
Home-page: https://github.com/qux-bbb/qinteract
Author: qux-bbb
Author-email: 1147635419@qq.com
License: UNKNOWN
Platform: UNKNOWN
